LICENSE
MANIFEST.in
README.md
drparse.py
requirements.txt
setup.py
drparse.egg-info/PKG-INFO
drparse.egg-info/SOURCES.txt
drparse.egg-info/dependency_links.txt
drparse.egg-info/requires.txt
drparse.egg-info/top_level.txt