Metadata-Version: 1.1
Name: drparse
Version: 0.0.1
Summary: Parse dates out of a textual string
Home-page: https://github.com/hampsterx/drparse
Author: Tim van der Hulst
Author-email: tim.vdh@gmail.com
License: GNU GENERAL PUBLIC LICENSE
